{
  "id": "3888212",
  "name": "cate",
  "font_family": "iconfont",
  "css_prefix_text": "",
  "description": "",
  "glyphs": [
    {
      "icon_id": "836525",
      "name": "external-link-square",
      "font_class": "externallinksquare",
      "unicode": "e6d8",
      "unicode_decimal": 59096
    },
    {
      "icon_id": "34190685",
      "name": "下拉-copy",
      "font_class": "down_arrow",
      "unicode": "e89f",
      "unicode_decimal": 59551
    },
    {
      "icon_id": "4765745",
      "name": "up-circle",
      "font_class": "up-circle",
      "unicode": "e785",
      "unicode_decimal": 59269
    }
  ]
}
